croco_selenium/__init__.py
croco_selenium/_croco_driver.py
croco_selenium/action_performer.py
croco_selenium/actions.py
croco_selenium/chrome_driver.py
croco_selenium/decorators.py
croco_selenium/exceptions.py
croco_selenium/types.py
croco_selenium/utils.py
croco_selenium-0.1.6.post2.dist-info/LICENSE
croco_selenium-0.1.6.post2.dist-info/METADATA
croco_selenium-0.1.6.post2.dist-info/WHEEL
croco_selenium-0.1.6.post2.dist-info/RECORD
