Metadata-Version: 2.1
Name: croco_selenium
Version: 0.1.6.post2
Summary: The package providing ways to interact with Selenium Web Driver actions, such as clicking, sending keys etc.
Home-page: https://github.com/CrocoFactory/croco-selenium
License: MIT
Author: Alexey
Author-email: axbelenkov@gmail.com
Requires-Python: >=3.11,<4.0
Classifier: Development Status :: 4 - Beta
Classifier: Intended Audience :: Developers
Classifier: License :: OSI Approved :: MIT License
Classifier: Operating System :: MacOS
Classifier: Operating System :: Microsoft :: Windows
Classifier: Programming Language :: Python :: 3
Classifier: Programming Language :: Python :: 3.11
Classifier: Programming Language :: Python :: 3.12
Classifier: Programming Language :: Python :: 3 :: Only
Classifier: Topic :: Software Development :: Libraries :: Python Modules
Classifier: Topic :: Software Development :: Testing
Requires-Dist: selenium (>=4.16.0,<5.0.0)
Project-URL: Repository, https://github.com/CrocoFactory/croco-selenium
